cymongoose/__init__.py
cymongoose/_mongoose.cp310-win_amd64.pyd
cymongoose/_mongoose.pyi
cymongoose-0.1.7.dist-info/licenses/LICENSE
cymongoose-0.1.7.dist-info/METADATA
cymongoose-0.1.7.dist-info/WHEEL
cymongoose-0.1.7.dist-info/top_level.txt
cymongoose-0.1.7.dist-info/RECORD
